Semana 4/mcu.v
//Definición del microcontrolador
module mcu(
    input clk,  //Reloj del microcontrolador
    input rst   //Reset del microcontrolador
);

//Buses con la memoria de programa (IMEM)
    wire [31:0] instr; //Instrucción de entrada
    wire [31:0] iaddr; //Dirección en la IMEM

//Buses con la memoria de datos (DMEM)
    wire [31:0] daddr;     //Dirección en la DMEM
    wire [31:0] ddata_in;  //Bus de datos DMEM (entrada)
    wire [31:0] ddata_out; //Bus de datos DMEM (salida)
    wire dwr_en;           //Señales del bus de control DMEM
    wire drd_en;


// Instancia del microprocesador RISCV
riscv cpu (
    .rst(rst),
    .clk(clk),
    .instr(instr),
    .iaddr(iaddr),
    .daddr(daddr),
    .ddata_in(ddata_in),
    .ddata_out(ddata_out),
    .dwr_en(dwr_en),
    .drd_en(drd_en)
);


// Instancia de la memoria de programa
rom4096x32 IMEM(
    .data(instr),
    .addr(iaddr[13:2])
);


endmodule

module rom4096x32 (
    input wire [11:0] addr,       // Dirección (4096 palabras -> 12 bits)
    output reg [31:0] data        // Datos de 32 bits
);
 always @(*) begin
        case(addr)
  // add x3, x0, x0
            12'd0: data = 32'h000001B3;

            // add x5, x0, x0
            12'd1: data = 32'h000002B3;

            // addi x6, x0, 5
            12'd2: data = 32'h00500313;

            // do1: add x3, x3, x5
            12'd3: data = 32'h005181B3;

            // addi x5, x5, 1
            12'd4: data = 32'h00128293;

            // blt x5, x6, do1
            12'd5: data = 32'hFE62CCE3;

            // finwhile: add x12, x3, x0
            12'd6: data = 32'h00018633;

            // NOP
            default: data = 32'h00000013;

        endcase
    end

endmodule

alu.v
module alu (
    input  [31:0] a,
    input  [31:0] b,
    input  [3:0]  op,
    output reg [31:0] ALU_out
);

  always @(*) begin
    case (op)
      4'b0000: ALU_out = a + b;                  // ADD
      4'b1000: ALU_out = a - b;                  // SUB
      4'b0001: ALU_out = a << b[4:0];            // SLL
      4'b0010: ALU_out = ($signed(a) < $signed(b)) ? 32'b1 : 32'b0; // SLT
      4'b0011: ALU_out = (a < b) ? 32'b1 : 32'b0; // SLTU
      4'b0100: ALU_out = a ^ b;                  // XOR
      4'b0101: ALU_out = a >> b[4:0];            // SRL
      4'b1101: ALU_out = $signed(a) >>> b[4:0];  // SRA
      4'b0110: ALU_out = a | b;                  // OR
      4'b0111: ALU_out = a & b;                  // AND
      default: ALU_out = 32'h00000000;
    endcase
  end

endmodule

register_file.v
module register_file (
    input clk,
    input wr_en,
    input [4:0] wr_index,
    input [31:0] wr_data,
    input [4:0] rd_index1,
    output [31:0] rd_data1,
    input [4:0] rd_index2,
    output [31:0] rd_data2
);

  // Arreglo de 32 registros de 32 bits (debe llamarse 'mem')
  reg [31:0] mem [0:31];

  // Lectura combinacional: si se pide el registro x0, devuelve 0
  assign rd_data1 = (rd_index1 == 5'b0) ? 32'b0 : mem[rd_index1];
  assign rd_data2 = (rd_index2 == 5'b0) ? 32'b0 : mem[rd_index2];

  // Escritura síncrona en el flanco de subida de reloj
  always @(posedge clk) begin
    if (wr_en && (wr_index != 5'b0)) begin
      mem[wr_index] <= wr_data;
    end
  end

endmodule

Semana 3/riscv3.v
module riscv (
    input clk,
    input rst,
    input [31:0] instr,

    // Conexion con IMEM
    output wire [31:0] iaddr,

    // Conexion con DMEM
    output wire [31:0] daddr,
    input wire [31:0] ddata_in,
    output wire [31:0] ddata_out,
    output wire dwr_en,
    output wire drd_en
);

// 1. CONTADOR DE PROGRAMA
// 

reg [31:0] PC;

// Direccion hacia la memoria de instrucciones
assign iaddr = PC;


// 2. CONTROL DE CICLOS

reg state_fetch;
reg state_decode;
reg state_execute;

// Contador en anillo de tres estados
always @(negedge clk) begin
    if (rst) begin
        state_fetch   <= 1'b1;
        state_decode  <= 1'b0;
        state_execute <= 1'b0;
    end
    else begin
        state_fetch   <= state_execute;
        state_decode  <= state_fetch;
        state_execute <= state_decode;
    end
end


// 3. REGISTRO DE INSTRUCCION
// 

reg [31:0] IR;

always @(posedge clk) begin
    if (rst)
        IR <= 32'd0;
    else if (state_fetch)
        IR <= instr;
end


// 4. CAMPOS DE LA INSTRUCCION

wire [6:0] funct7;
wire [4:0] rs2;
wire [4:0] rs1;
wire [2:0] funct3;
wire [4:0] rd;
wire [6:0] opcode;

assign funct7 = IR[31:25];
assign rs2    = IR[24:20];
assign rs1    = IR[19:15];
assign funct3 = IR[14:12];
assign rd     = IR[11:7];
assign opcode = IR[6:0];


// 5. REGISTER FILE Y ALU

wire [31:0] src1_value;
wire [31:0] src2_value;

wire [31:0] alu_a;
wire [31:0] alu_b;
wire [31:0] alu_out;

wire [3:0] alu_op;
wire wr_en;

 
// 6. SEÑALES DE DECODIFICACION


wire [10:0] dec_bits;
wire [9:0] dec_bits2;

// Instrucciones tipo R
wire is_add;
wire is_sub;
wire is_sll;
wire is_slt;
wire is_sltu;
wire is_xor;
wire is_srl;
wire is_sra;
wire is_or;
wire is_and;

// Instrucciones tipo I aritmeticas
wire is_addi;
wire is_xori;
wire is_ori;
wire is_andi;

// Instrucciones tipo B
wire is_beq;
wire is_bne;
wire is_blt;
wire is_bge;
wire is_bltu;
wire is_bgeu;

// Tipos de instrucciones
wire is_valid;
wire is_u_instr;
wire is_j_instr;
wire is_b_instr;
wire is_s_instr;
wire is_r_instr;
wire is_i_instr;

// Inmediato
wire [31:0] imm;
wire imm_valid;

// 7. INSTANCIA DEL REGISTER FILE


register_file rf (
    .clk(clk),
    .wr_en(wr_en),
    .wr_index(rd),
    .wr_data(alu_out),
    .rd_index1(rs1),
    .rd_data1(src1_value),
    .rd_index2(rs2),
    .rd_data2(src2_value)
);


// 
// 8. INSTANCIA DE LA ALU

alu rv_alu (
    .a(alu_a),
    .b(alu_b),
    .ALU_out(alu_out),
    .op(alu_op)
);


// 9. CONEXION REGISTER FILE - ALU
// 

assign alu_a = src1_value;

// MUX para seleccionar registro o inmediato
assign alu_b = imm_valid ? imm : src2_value;


// 10. UNIDAD DE CONTROL

assign is_valid = (opcode[1:0] == 2'b11);


// 
// 11. DETECCION DE FORMATOS

// Tipo U
assign is_u_instr =
    (opcode[6:2] == 5'b00101) ||
    (opcode[6:2] == 5'b01101);

// Tipo J
assign is_j_instr =
    (opcode[6:2] == 5'b11011);

// Tipo B
assign is_b_instr =
    (opcode[6:2] == 5'b11000);

// Tipo S
assign is_s_instr =
    (opcode[6:2] == 5'b01000) ||
    (opcode[6:2] == 5'b01001);

// Tipo R
assign is_r_instr =
    (opcode[6:2] == 5'b01011) ||
    (opcode[6:2] == 5'b01100) ||
    (opcode[6:2] == 5'b01110) ||
    (opcode[6:2] == 5'b10100);

// Tipo I
assign is_i_instr =
    (opcode[6:2] == 5'b00000) ||
    (opcode[6:2] == 5'b00001) ||
    (opcode[6:2] == 5'b00100) ||
    (opcode[6:2] == 5'b00110) ||
    (opcode[6:2] == 5'b11001) ||
    (opcode[6:2] == 5'b11100);


// 12. DECODIFICACION DE INSTRUCCIONES BRANCH

assign is_beq =
    is_b_instr && (funct3 == 3'b000);

assign is_bne =
    is_b_instr && (funct3 == 3'b001);

assign is_blt =
    is_b_instr && (funct3 == 3'b100);

assign is_bge =
    is_b_instr && (funct3 == 3'b101);

assign is_bltu =
    is_b_instr && (funct3 == 3'b110);

assign is_bgeu =
    is_b_instr && (funct3 == 3'b111);



// 13. GENERADOR DE INMEDIATOS

assign imm =

    // Tipo I
    is_i_instr ?
    {
        {20{IR[31]}},
        IR[31:20]
    } :

    // Tipo S
    is_s_instr ?
    {
        {20{IR[31]}},
        IR[31:25],
        IR[11:7]
    } :

    // Tipo B
    is_b_instr ?
    {
        {19{IR[31]}},
        IR[31],
        IR[7],
        IR[30:25],
        IR[11:8],
        1'b0
    } :

    // Tipo U
    is_u_instr ?
    {
        IR[31:12],
        12'b0
    } :

    // Tipo J
    is_j_instr ?
    {
        {11{IR[31]}},
        IR[31],
        IR[19:12],
        IR[20],
        IR[30:21],
        1'b0
    } :

    32'b0;


// 
// 14. VALIDEZ DEL INMEDIATO
// 

assign imm_valid =
    is_i_instr |
    is_s_instr |
    is_b_instr |
    is_u_instr |
    is_j_instr;


// 
// 15. WRITE ENABLE DEL REGISTER FILE
// REQUERIMIENTO E

// Solo escribe durante EXECUTE
assign wr_en =
    state_execute &
    (
        is_r_instr |
        is_i_instr |
        is_u_instr |
        is_j_instr
    );


// 16. DECODIFICACION TIPO R

assign dec_bits = {
    funct7[5],
    funct3,
    opcode
};

assign is_add =
    (dec_bits == 11'b0_000_0110011);

assign is_sub =
    (dec_bits == 11'b1_000_0110011);

assign is_sll =
    (dec_bits == 11'b0_001_0110011);

assign is_slt =
    (dec_bits == 11'b0_010_0110011);

assign is_sltu =
    (dec_bits == 11'b0_011_0110011);

assign is_xor =
    (dec_bits == 11'b0_100_0110011);

assign is_srl =
    (dec_bits == 11'b0_101_0110011);

assign is_sra =
    (dec_bits == 11'b1_101_0110011);

assign is_or =
    (dec_bits == 11'b0_110_0110011);

assign is_and =
    (dec_bits == 11'b0_111_0110011);


// 17. DECODIFICACION TIPO I ARITMETICA
// 

assign dec_bits2 = {
    funct3,
    opcode
};

assign is_addi =
    (dec_bits2 == 10'b000_0010011);

assign is_xori =
    (dec_bits2 == 10'b100_0010011);

assign is_ori =
    (dec_bits2 == 10'b110_0010011);

assign is_andi =
    (dec_bits2 == 10'b111_0010011);


// 
// 18. CONTROL DE LA ALU
// 

assign alu_op =

    is_addi ? 4'b0000 :

    is_xori ? 4'b0100 :

    is_ori  ? 4'b0110 :

    is_andi ? 4'b0111 :

    // Instrucciones tipo R
    {funct7[5], funct3};


// 
// 19. INTERFAZ CON DMEM
// Temporalmente deshabilitada
// 

assign daddr     = 32'b0;
assign ddata_out = 32'b0;
assign dwr_en    = 1'b0;
assign drd_en    = 1'b0;


// 20. REQUERIMIENTO F: LOGICA DEL PC

// Senales de control del contador de programa
wire taken_br;
wire [31:0] br_tgt_pc;
wire [31:0] pc4;
wire [31:0] next_pc;


// 20.1 COMPARADOR DE SALTOS CONDICIONALES

assign taken_br =

    // BEQ: iguales
    is_beq ? (src1_value == src2_value) :

    // BNE: diferentes
    is_bne ? (src1_value != src2_value) :

    // BLT: menor con signo
    is_blt ?
        ($signed(src1_value) < $signed(src2_value)) :

    // BGE: mayor o igual con signo
    is_bge ?
        ($signed(src1_value) >= $signed(src2_value)) :

    // BLTU: menor sin signo
    is_bltu ? (src1_value < src2_value) :

    // BGEU: mayor o igual sin signo
    is_bgeu ? (src1_value >= src2_value) :

    // No hay salto condicional
    1'b0;


// 20.2 SUMADORES DEL PC

// Direccion destino del salto
assign br_tgt_pc = PC + imm;

// Siguiente instruccion secuencial
assign pc4 = PC + 32'd4;


// 20.3 MULTIPLEXOR DEL PC

// Salto condicional verdadero o JAL:
// next_pc = PC + imm
//
// En otro caso:
// next_pc = PC + 4

assign next_pc =
    (taken_br || is_j_instr) ? br_tgt_pc : pc4;


// 20.4 ACTUALIZACION DEL REGISTRO PC

// Reset sincronico y actualizacion solo durante EXECUTE

always @(posedge clk) begin

    if (rst)
        PC <= 32'd0;

    else if (state_execute)
        PC <= next_pc;

end

endmodule

Semana 3/Testbench/mcu_tb.v
`timescale 1ns/1ps

// Test bench para el microcontrolador
module tb_mcu;

  reg clk;
  reg rst;

  // Instancia del microcontrolador
  mcu mcuuq (
    .rst(rst),
    .clk(clk)
  );

  integer i;

  initial begin

    $dumpfile("tb_mcu.vcd");
    $dumpvars(0, tb_mcu);
 

    // Icarus no acepta mem[i] en una referencia jerarquica
    // dentro de $dumpvars.
   // Registros necesarios para la evidencia
    $dumpvars(0, mcuuq.cpu.rf.mem[3]);
    $dumpvars(0, mcuuq.cpu.rf.mem[5]);
    $dumpvars(0, mcuuq.cpu.rf.mem[6]);
    $dumpvars(0, mcuuq.cpu.rf.mem[12]);

    #0;
    clk = 0;
    rst = 1;

    #9;
    rst = 0;

    #240;  // Termina después de 60 ciclos de reloj
    #16;

    $finish;

  end

  always begin
    #2 clk = !clk;
  end

endmodule

Semana 4/tb_mcu.vcd
$date
	Sat Oct  3 05:34:30 2026
$end
$version
	Icarus Verilog
$end
$timescale
	1ps
$end
$scope module tb_mcu $end
$var reg 1 ! clk $end
$var reg 1 " rst $end
$scope module mcuuq $end
$var wire 1 ! clk $end
$var wire 32 # daddr [31:0] $end
$var wire 32 $ ddata_in [31:0] $end
$var wire 32 % ddata_out [31:0] $end
$var wire 1 & drd_en $end
$var wire 1 ' dwr_en $end
$var wire 1 " rst $end
$var wire 32 ( instr [31:0] $end
$var wire 32 ) iaddr [31:0] $end
$scope module IMEM $end
$var wire 12 * addr [11:0] $end
$var reg 32 + data [31:0] $end
$upscope $end
$scope module cpu $end
$var wire 32 , alu_a [31:0] $end
$var wire 1 ! clk $end
$var wire 32 - daddr [31:0] $end
$var wire 32 . ddata_in [31:0] $end
$var wire 32 / ddata_out [31:0] $end
$var wire 1 & drd_en $end
$var wire 1 ' dwr_en $end
$var wire 32 0 iaddr [31:0] $end
$var wire 1 1 imm_valid $end
$var wire 32 2 instr [31:0] $end
$var wire 1 3 is_beq $end
$var wire 1 4 is_bge $end
$var wire 1 5 is_bgeu $end
$var wire 1 6 is_blt $end
$var wire 1 7 is_bltu $end
$var wire 1 8 is_bne $end
$var wire 1 9 is_i_instr $end
$var wire 1 : is_r_instr $end
$var wire 1 ; is_s_instr $end
$var wire 1 < is_u_instr $end
$var wire 1 " rst $end
$var wire 1 = wr_en $end
$var wire 1 > taken_br $end
$var wire 32 ? src2_value [31:0] $end
$var wire 32 @ src1_value [31:0] $end
$var wire 5 A rs2 [4:0] $end
$var wire 5 B rs1 [4:0] $end
$var wire 5 C rd [4:0] $end
$var wire 32 D pc4 [31:0] $end
$var wire 7 E opcode [6:0] $end
$var wire 32 F next_pc [31:0] $end
$var wire 1 G is_xori $end
$var wire 1 H is_xor $end
$var wire 1 I is_valid $end
$var wire 1 J is_sub $end
$var wire 1 K is_srl $end
$var wire 1 L is_sra $end
$var wire 1 M is_sltu $end
$var wire 1 N is_slt $end
$var wire 1 O is_sll $end
$var wire 1 P is_ori $end
$var wire 1 Q is_or $end
$var wire 1 R is_j_instr $end
$var wire 1 S is_b_instr $end
$var wire 1 T is_andi $end
$var wire 1 U is_and $end
$var wire 1 V is_addi $end
$var wire 1 W is_add $end
$var wire 32 X imm [31:0] $end
$var wire 7 Y funct7 [6:0] $end
$var wire 3 Z funct3 [2:0] $end
$var wire 10 [ dec_bits2 [9:0] $end
$var wire 11 \ dec_bits [10:0] $end
$var wire 32 ] br_tgt_pc [31:0] $end
$var wire 32 ^ alu_out [31:0] $end
$var wire 4 _ alu_op [3:0] $end
$var wire 32 ` alu_b [31:0] $end
$var reg 32 a IR [31:0] $end
$var reg 32 b PC [31:0] $end
$var reg 1 c state_decode $end
$var reg 1 d state_execute $end
$var reg 1 e state_fetch $end
$scope module rf $end
$var wire 1 ! clk $end
$var wire 5 f rd_index1 [4:0] $end
$var wire 5 g rd_index2 [4:0] $end
$var wire 1 = wr_en $end
$var wire 5 h wr_index [4:0] $end
$var wire 32 i wr_data [31:0] $end
$var wire 32 j rd_data2 [31:0] $end
$var wire 32 k rd_data1 [31:0] $end
$upscope $end
$scope module rv_alu $end
$var wire 32 l a [31:0] $end
$var wire 32 m b [31:0] $end
$var wire 4 n op [3:0] $end
$var reg 32 o ALU_out [31:0] $end
$upscope $end
$upscope $end
$upscope $end
$upscope $end
$scope module tb_mcu $end
$scope module mcuuq $end
$scope module cpu $end
$scope module rf $end
$var reg 32 p \mem[3] [31:0] $end
$upscope $end
$upscope $end
$upscope $end
$upscope $end
$scope module tb_mcu $end
$scope module mcuuq $end
$scope module cpu $end
$scope module rf $end
$var reg 32 q \mem[5] [31:0] $end
$upscope $end
$upscope $end
$upscope $end
$upscope $end
$scope module tb_mcu $end
$scope module mcuuq $end
$scope module cpu $end
$scope module rf $end
$var reg 32 r \mem[6] [31:0] $end
$upscope $end
$upscope $end
$upscope $end
$upscope $end
$scope module tb_mcu $end
$scope module mcuuq $end
$scope module cpu $end
$scope module rf $end
$var reg 32 s \mem[12] [31:0] $end
$upscope $end
$upscope $end
$upscope $end
$upscope $end
$enddefinitions $end
$comment Show the parameter values. $end
$dumpall
$end
#0
$dumpvars
bx s
bx r
bx q
bx p
bx o
bx n
bx m
bx l
bx k
bx j
bx i
bx h
bx g
bx f
1e
0d
0c
bx b
bx a
bx `
bx _
bx ^
bx ]
bx \
bx [
bx Z
bx Y
bx X
xW
xV
xU
xT
xS
xR
xQ
xP
xO
xN
xM
xL
xK
xJ
xI
xH
xG
bx F
bx E
bx D
bx C
bx B
bx A
bx @
bx ?
x>
0=
x<
x;
x:
x9
x8
x7
x6
x5
x4
x3
bx 2
x1
bx 0
b0 /
bz .
b0 -
bx ,
bx +
bx *
bx )
bx (
0'
0&
b0 %
bz $
b0 #
1"
0!
$end
#2000
11
b0 ]
19
b100 F
0:
b0 `
b0 m
b0 ^
b0 i
b0 o
0>
0<
0;
b0 _
b0 n
b0 X
b0 ?
b0 j
b0 ,
b0 l
b0 @
b0 k
03
08
06
04
07
05
0I
0R
0S
0W
0J
0O
0N
0M
0H
0K
0L
0Q
0U
b0 \
0V
0G
0P
0T
b0 [
b110110011 (
b110110011 +
b110110011 2
b0 Y
b0 A
b0 g
b0 B
b0 f
b0 Z
b0 C
b0 h
b0 E
b0 *
b0 a
b100 D
b0 )
b0 0
b0 b
1!
#4000
0!
#6000
1!
#8000
0!
#9000
0"
#10000
01
09
1:
1I
1W
b110011 \
b110011 [
b11 C
b11 h
b110011 E
b110110011 a
1!
#12000
1c
0e
0!
#14000
1!
#16000
1=
1d
0c
0!
#18000
b1010110011 (
b1010110011 +
b1010110011 2
b1000 F
b1 *
b0 p
b100 ]
b1000 D
b100 )
b100 0
b100 b
1!
#20000
0=
0d
1e
0!
#22000
b101 C
b101 h
b1010110011 a
1!
#24000
1c
0e
0!
#26000
1!
#28000
1=
1d
0c
0!
#30000
b10100000000001100010011 (
b10100000000001100010011 +
b10100000000001100010011 2
b1100 F
b10 *
b1000 ]
b1100 D
b1000 )
b1000 0
b1000 b
b0 q
1!
#32000
0=
0d
1e
0!
#34000
b101 ^
b101 i
b101 o
b101 `
b101 m
11
b1101 ]
b101 X
19
0:
0W
b10011 \
1V
b10011 [
b101 A
b101 g
b110 C
b110 h
b10011 E
b10100000000001100010011 a
1!
#36000
1c
0e
0!
#38000
1!
#40000
1=
1d
0c
0!
#42000
b10100011000000110110011 (
b10100011000000110110011 +
b10100011000000110110011 2
b10000 F
b11 *
b101 r
b10001 ]
b10000 D
b1100 )
b1100 0
b1100 b
1!
#44000
0=
0d
1e
0!
#46000
01
b0 ^
b0 i
b0 o
b0 `
b0 m
b1100 ]
b0 X
09
1:
1W
b110011 \
0V
b110011 [
b11 B
b11 f
b11 C
b11 h
b110011 E
b10100011000000110110011 a
1!
#48000
1c
0e
0!
#50000
1!
#52000
1=
1d
0c
0!
#54000
b100101000001010010011 (
b100101000001010010011 +
b100101000001010010011 2
b10100 F
b100 *
b10000 ]
b10100 D
b10000 )
b10000 0
b10000 b
b0 p
1!
#56000
0=
0d
1e
0!
#58000
11
b10001 ]
b1 X
19
b1 ^
b1 i
b1 o
0:
b1 `
b1 m
bx ?
bx j
0W
b10011 \
1V
b10011 [
b1 A
b1 g
b101 B
b101 f
b101 C
b101 h
b10011 E
b100101000001010010011 a
1!
#60000
1c
0e
0!
#62000
1!
#64000
1=
1d
0c
0!
#66000
b10 ^
b10 i
b10 o
b11111110011000101100110011100011 (
b11111110011000101100110011100011 +
b11111110011000101100110011100011 2
b1 ,
b1 l
b1 @
b1 k
b11000 F
b101 *
b1 q
b10101 ]
b11000 D
b10100 )
b10100 0
b10100 b
1!
#68000
0=
0d
1e
0!
#70000
b1100 F
b1100 _
b1100 n
09
1>
b0 ^
b0 i
b0 o
b11111111111111111111111111111000 `
b11111111111111111111111111111000 m
b101 ?
b101 j
b1100 ]
b11111111111111111111111111111000 X
16
1S
b11001100011 \
0V
b1001100011 [
b1111111 Y
b110 A
b110 g
b100 Z
b11001 C
b11001 h
b1100011 E
b11111110011000101100110011100011 a
1!
#72000
1c
0e
0!
#74000
1!
#76000
1d
0c
0!
#78000
b10100011000000110110011 (
b10100011000000110110011 +
b10100011000000110110011 2
b100 F
b11 *
b100 ]
b10000 D
b1100 )
b1100 0
b1100 b
1!
#80000
0d
1e
0!
#82000
b1 ^
b1 i
b1 o
b0 _
b0 n
b10000 F
b1 `
b1 m
0>
b1100 ]
b0 X
01
1:
1W
b1 ?
b1 j
b0 ,
b0 l
b0 @
b0 k
06
0S
0J
b110011 \
b110011 [
b0 Y
b101 A
b101 g
b11 B
b11 f
b0 Z
b11 C
b11 h
b110011 E
b10100011000000110110011 a
1!
#84000
1c
0e
0!
#86000
1!
#88000
1=
1d
0c
0!
#90000
b10 ^
b10 i
b10 o
b100101000001010010011 (
b100101000001010010011 +
b100101000001010010011 2
b1 ,
b1 l
b1 @
b1 k
b10100 F
b100 *
b1 p
b10000 ]
b10100 D
b10000 )
b10000 0
b10000 b
1!
#92000
0=
0d
1e
0!
#94000
11
b10001 ]
b1 X
19
b10 ^
b10 i
b10 o
0:
b1 `
b1 m
bx ?
bx j
0W
b10011 \
1V
b10011 [
b1 A
b1 g
b101 B
b101 f
b101 C
b101 h
b10011 E
b100101000001010010011 a
1!
#96000
1c
0e
0!
#98000
1!
#100000
1=
1d
0c
0!
#102000
b11111110011000101100110011100011 (
b11111110011000101100110011100011 +
b11111110011000101100110011100011 2
b11 ^
b11 i
b11 o
b11000 F
b101 *
b10 ,
b10 l
b10 @
b10 k
b10101 ]
b11000 D
b10100 )
b10100 0
b10100 b
b10 q
1!
#104000
0=
0d
1e
0!
#106000
b1100 F
b1100 _
b1100 n
09
1>
b0 ^
b0 i
b0 o
b11111111111111111111111111111000 `
b11111111111111111111111111111000 m
b101 ?
b101 j
b1100 ]
b11111111111111111111111111111000 X
16
1S
b11001100011 \
0V
b1001100011 [
b1111111 Y
b110 A
b110 g
b100 Z
b11001 C
b11001 h
b1100011 E
b11111110011000101100110011100011 a
1!
#108000
1c
0e
0!
#110000
1!
#112000
1d
0c
0!
#114000
b10100011000000110110011 (
b10100011000000110110011 +
b10100011000000110110011 2
b100 F
b11 *
b100 ]
b10000 D
b1100 )
b1100 0
b1100 b
1!
#116000
0d
1e
0!
#118000
b11 ^
b11 i
b11 o
b0 _
b0 n
b10000 F
b10 `
b10 m
0>
b1100 ]
b0 X
01
1:
1W
b10 ?
b10 j
b1 ,
b1 l
b1 @
b1 k
06
0S
0J
b110011 \
b110011 [
b0 Y
b101 A
b101 g
b11 B
b11 f
b0 Z
b11 C
b11 h
b110011 E
b10100011000000110110011 a
1!
#120000
1c
0e
0!
#122000
1!
#124000
1=
1d
0c
0!
#126000
b100101000001010010011 (
b100101000001010010011 +
b100101000001010010011 2
b101 ^
b101 i
b101 o
b10100 F
b100 *
b11 ,
b11 l
b11 @
b11 k
b10000 ]
b10100 D
b10000 )
b10000 0
b10000 b
b11 p
1!
#128000
0=
0d
1e
0!
#130000
11
b10001 ]
b1 X
19
0:
b1 `
b1 m
b11 ^
b11 i
b11 o
bx ?
bx j
b10 ,
b10 l
b10 @
b10 k
0W
b10011 \
1V
b10011 [
b1 A
b1 g
b101 B
b101 f
b101 C
b101 h
b10011 E
b100101000001010010011 a
1!
#132000
1c
0e
0!
#134000
1!
#136000
1=
1d
0c
0!
#138000
b100 ^
b100 i
b100 o
b11111110011000101100110011100011 (
b11111110011000101100110011100011 +
b11111110011000101100110011100011 2
b11 ,
b11 l
b11 @
b11 k
b11000 F
b101 *
b11 q
b10101 ]
b11000 D
b10100 )
b10100 0
b10100 b
1!
#140000
0=
0d
1e
0!
#142000
b1100 F
b1100 _
b1100 n
09
1>
b0 ^
b0 i
b0 o
b11111111111111111111111111111000 `
b11111111111111111111111111111000 m
b101 ?
b101 j
b1100 ]
b11111111111111111111111111111000 X
16
1S
b11001100011 \
0V
b1001100011 [
b1111111 Y
b110 A
b110 g
b100 Z
b11001 C
b11001 h
b1100011 E
b11111110011000101100110011100011 a
1!
#144000
1c
0e
0!
#146000
1!
#148000
1d
0c
0!
#150000
b10100011000000110110011 (
b10100011000000110110011 +
b10100011000000110110011 2
b100 F
b11 *
b100 ]
b10000 D
b1100 )
b1100 0
b1100 b
1!
#152000
0d
1e
0!
#154000
b110 ^
b110 i
b110 o
b0 _
b0 n
b10000 F
b11 `
b11 m
0>
b1100 ]
b0 X
01
1:
1W
b11 ?
b11 j
06
0S
0J
b110011 \
b110011 [
b0 Y
b101 A
b101 g
b11 B
b11 f
b0 Z
b11 C
b11 h
b110011 E
b10100011000000110110011 a
1!
#156000
1c
0e
0!
#158000
1!
#160000
1=
1d
0c
0!
#162000
b1001 ^
b1001 i
b1001 o
b100101000001010010011 (
b100101000001010010011 +
b100101000001010010011 2
b110 ,
b110 l
b110 @
b110 k
b10100 F
b100 *
b110 p
b10000 ]
b10100 D
b10000 )
b10000 0
b10000 b
1!
#164000
0=
0d
1e
0!
#166000
11
b10001 ]
b1 X
19
0:
b1 `
b1 m
b100 ^
b100 i
b100 o
bx ?
bx j
b11 ,
b11 l
b11 @
b11 k
0W
b10011 \
1V
b10011 [
b1 A
b1 g
b101 B
b101 f
b101 C
b101 h
b10011 E
b100101000001010010011 a
1!
#168000
1c
0e
0!
#170000
1!
#172000
1=
1d
0c
0!
#174000
b11111110011000101100110011100011 (
b11111110011000101100110011100011 +
b11111110011000101100110011100011 2
b101 ^
b101 i
b101 o
b11000 F
b101 *
b100 ,
b100 l
b100 @
b100 k
b10101 ]
b11000 D
b10100 )
b10100 0
b10100 b
b100 q
1!
#176000
0=
0d
1e
0!
#178000
b1100 F
b1100 _
b1100 n
09
1>
b0 ^
b0 i
b0 o
b11111111111111111111111111111000 `
b11111111111111111111111111111000 m
b101 ?
b101 j
b1100 ]
b11111111111111111111111111111000 X
16
1S
b11001100011 \
0V
b1001100011 [
b1111111 Y
b110 A
b110 g
b100 Z
b11001 C
b11001 h
b1100011 E
b11111110011000101100110011100011 a
1!
#180000
1c
0e
0!
#182000
1!
#184000
1d
0c
0!
#186000
b10100011000000110110011 (
b10100011000000110110011 +
b10100011000000110110011 2
b100 F
b11 *
b100 ]
b10000 D
b1100 )
b1100 0
b1100 b
1!
#188000
0d
1e
0!
#190000
b1010 ^
b1010 i
b1010 o
b0 _
b0 n
b10000 F
b100 `
b100 m
0>
b1100 ]
b0 X
01
1:
1W
b100 ?
b100 j
b110 ,
b110 l
b110 @
b110 k
06
0S
0J
b110011 \
b110011 [
b0 Y
b101 A
b101 g
b11 B
b11 f
b0 Z
b11 C
b11 h
b110011 E
b10100011000000110110011 a
1!
#192000
1c
0e
0!
#194000
1!
#196000
1=
1d
0c
0!
#198000
b100101000001010010011 (
b100101000001010010011 +
b100101000001010010011 2
b1110 ^
b1110 i
b1110 o
b10100 F
b100 *
b1010 ,
b1010 l
b1010 @
b1010 k
b10000 ]
b10100 D
b10000 )
b10000 0
b10000 b
b1010 p
1!
#200000
0=
0d
1e
0!
#202000
11
b10001 ]
b1 X
19
0:
b1 `
b1 m
b101 ^
b101 i
b101 o
bx ?
bx j
b100 ,
b100 l
b100 @
b100 k
0W
b10011 \
1V
b10011 [
b1 A
b1 g
b101 B
b101 f
b101 C
b101 h
b10011 E
b100101000001010010011 a
1!
#204000
1c
0e
0!
#206000
1!
#208000
1=
1d
0c
0!
#210000
b110 ^
b110 i
b110 o
b11111110011000101100110011100011 (
b11111110011000101100110011100011 +
b11111110011000101100110011100011 2
b101 ,
b101 l
b101 @
b101 k
b11000 F
b101 *
b101 q
b10101 ]
b11000 D
b10100 )
b10100 0
b10100 b
1!
#212000
0=
0d
1e
0!
#214000
b11000 F
b1100 _
b1100 n
09
0>
b0 ^
b0 i
b0 o
b11111111111111111111111111111000 `
b11111111111111111111111111111000 m
b101 ?
b101 j
b1100 ]
b11111111111111111111111111111000 X
16
1S
b11001100011 \
0V
b1001100011 [
b1111111 Y
b110 A
b110 g
b100 Z
b11001 C
b11001 h
b1100011 E
b11111110011000101100110011100011 a
1!
#216000
1c
0e
0!
#218000
1!
#220000
1d
0c
0!
#222000
b11000011000110011 (
b11000011000110011 +
b11000011000110011 2
b11100 F
b110 *
b10000 ]
b11100 D
b11000 )
b11000 0
b11000 b
1!
#224000
0d
1e
0!
#226000
b1010 ^
b1010 i
b1010 o
b0 _
b0 n
b0 `
b0 m
b11000 ]
b0 X
01
1:
1W
b1010 ,
b1010 l
b1010 @
b1010 k
b0 ?
b0 j
06
0S
0J
b110011 \
b110011 [
b0 Y
b0 A
b0 g
b11 B
b11 f
b0 Z
b1100 C
b1100 h
b110011 E
b11000011000110011 a
1!
#228000
1c
0e
0!
#230000
1!
#232000
1=
1d
0c
0!
#234000
b10011 (
b10011 +
b10011 2
b100000 F
b111 *
b1010 s
b11100 ]
b100000 D
b11100 )
b11100 0
b11100 b
1!
#236000
0=
0d
1e
0!
#238000
11
19
0:
b0 ^
b0 i
b0 o
b0 ,
b0 l
b0 @
b0 k
0W
b10011 \
1V
b10011 [
b0 B
b0 f
b0 C
b0 h
b10011 E
b10011 a
1!
#240000
1c
0e
0!
#242000
1!
#244000
1=
1d
0c
0!
#246000
b100100 F
b1000 *
b100000 ]
b100100 D
b100000 )
b100000 0
b100000 b
1!
#248000
0=
0d
1e
0!
#250000
1!
#252000
1c
0e
0!
#254000
1!
#256000
1=
1d
0c
0!
#258000
b101000 F
b1001 *
b100100 ]
b101000 D
b100100 )
b100100 0
b100100 b
1!
#260000
0=
0d
1e
0!
#262000
1!
#264000
1c
0e
0!
